jupyterlab_translate/__init__.py
jupyterlab_translate/api.py
jupyterlab_translate/cli.py
jupyterlab_translate/constants.py
jupyterlab_translate/contributors.py
jupyterlab_translate/converters.py
jupyterlab_translate/finder.py
jupyterlab_translate/gettext_extract.py
jupyterlab_translate/hooks.py
jupyterlab_translate/index.js
jupyterlab_translate/plugin.py
jupyterlab_translate/pybabel_config.cfg
jupyterlab_translate/utils.py
jupyterlab_translate-1.3.7.dist-info/METADATA
jupyterlab_translate-1.3.7.dist-info/WHEEL
jupyterlab_translate-1.3.7.dist-info/entry_points.txt
jupyterlab_translate-1.3.7.dist-info/licenses/LICENSE.txt
jupyterlab_translate-1.3.7.dist-info/RECORD
