Metadata-Version: 2.3
Name: jupyterlab-translate
Version: 1.3.7
Summary: JupyterLab Language Pack Translations Helper
Project-URL: homepage, https://github.com/jupyterlab/jupyterlab-translate
Author-email: Project Jupyter Contributors <jupyter@googlegroups.com>
License: Copyright (c) 2020 Project Jupyter Contributors
License-File: LICENSE.txt
Keywords: hatch,jupyterlab,language,localization
Classifier: Framework :: Hatch
Classifier: Framework :: Jupyter
Classifier: Framework :: Jupyter :: JupyterLab
Classifier: License :: OSI Approved :: BSD License
Classifier: Programming Language :: Python
Classifier: Programming Language :: Python :: 3
Requires-Python: >=3.7
Requires-Dist: babel
Requires-Dist: click
Requires-Dist: copier-templates-extensions
Requires-Dist: copier>=9.2.0
Requires-Dist: crowdin-api-client
Requires-Dist: hatchling>=1.5
Requires-Dist: importlib-metadata>=4.8.3; python_version < '3.10'
Requires-Dist: jinja2-time
Requires-Dist: polib
Requires-Dist: pydantic
Requires-Dist: requests
Provides-Extra: test
Requires-Dist: hatch; extra == 'test'
Requires-Dist: pre-commit; extra == 'test'
Requires-Dist: pytest; extra == 'test'
Requires-Dist: pytest-cov; extra == 'test'
